{".class":"MypyFile","_fullname":"cherenkov.openclaw.feedback","future_import_flags":["annotations"],"is_partial_stub_package":false,"is_stub":false,"names":{".class":"SymbolTable","Any":{".class":"SymbolTableNode","cross_ref":"typing.Any","kind":"Gdef"},"HealingFeedbackStore":{".class":"SymbolTableNode","kind":"Gdef","node":{".class":"TypeInfo","_promote":[],"abstract_attributes":[],"alt_promote":null,"bases":["builtins.object"],"dataclass_transform_spec":null,"declared_metaclass":null,"defn":{".class":"ClassDef","fullname":"cherenkov.openclaw.feedback.HealingFeedbackStore","name":"HealingFeedbackStore","type_vars":[]},"deletable_attributes":[],"flags":[],"fullname":"cherenkov.openclaw.feedback.HealingFeedbackStore","has_param_spec_type":false,"metaclass_type":null,"metadata":{},"module_name":"cherenkov.openclaw.feedback","mro":["cherenkov.openclaw.feedback.HealingFeedbackStore","builtins.object"],"names":{".class":"SymbolTable","__init__":{".class":"SymbolTableNode","kind":"Mdef","node":{".class":"FuncDef","abstract_status":0,"arg_kinds":[0,1,1],"arg_names":["self","db_path","run_id"],"dataclass_transform_spec":null,"flags":[],"fullname":"cherenkov.openclaw.feedback.HealingFeedbackStore.__init__","name":"__init__","type":{".class":"CallableType","arg_kinds":[0,1,1],"arg_names":["self","db_path","run_id"],"arg_types":["cherenkov.openclaw.feedback.HealingFeedbackStore",{".class":"UnionType","items":["builtins.str",{".class":"NoneType"}]},{".class":"UnionType","items":["builtins.str",{".class":"NoneType"}]}],"bound_args":[],"def_extras":{"first_arg":"self"},"fallback":"builtins.function","from_concatenate":false,"implicit":false,"imprecise_arg_kinds":false,"is_ellipsis_args":false,"name":"__init__ of HealingFeedbackStore","ret_type":{".class":"NoneType"},"type_guard":null,"type_is":null,"unpack_kwargs":false,"variables":[]}}},"_connect":{".class":"SymbolTableNode","kind":"Mdef","node":{".class":"FuncDef","abstract_status":0,"arg_kinds":[0],"arg_names":["self"],"dataclass_transform_spec":null,"flags":[],"fullname":"cherenkov.openclaw.feedback.HealingFeedbackStore._connect","name":"_connect","type":{".class":"CallableType","arg_kinds":[0],"arg_names":["self"],"arg_types":["cherenkov.openclaw.feedback.HealingFeedbackStore"],"bound_args":[],"def_extras":{"first_arg":"self"},"fallback":"builtins.function","from_concatenate":false,"implicit":false,"imprecise_arg_kinds":false,"is_ellipsis_args":false,"name":"_connect of HealingFeedbackStore","ret_type":"sqlite3.dbapi2.Connection","type_guard":null,"type_is":null,"unpack_kwargs":false,"variables":[]}}},"_init_tables":{".class":"SymbolTableNode","kind":"Mdef","node":{".class":"FuncDef","abstract_status":0,"arg_kinds":[0],"arg_names":["self"],"dataclass_transform_spec":null,"flags":[],"fullname":"cherenkov.openclaw.feedback.HealingFeedbackStore._init_tables","name":"_init_tables","type":{".class":"CallableType","arg_kinds":[0],"arg_names":["self"],"arg_types":["cherenkov.openclaw.feedback.HealingFeedbackStore"],"bound_args":[],"def_extras":{"first_arg":"self"},"fallback":"builtins.function","from_concatenate":false,"implicit":false,"imprecise_arg_kinds":false,"is_ellipsis_args":false,"name":"_init_tables of HealingFeedbackStore","ret_type":{".class":"NoneType"},"type_guard":null,"type_is":null,"unpack_kwargs":false,"variables":[]}}},"_local":{".class":"SymbolTableNode","implicit":true,"kind":"Mdef","node":{".class":"Var","flags":["is_inferred"],"fullname":"cherenkov.openclaw.feedback.HealingFeedbackStore._local","name":"_local","type":"_thread._local"}},"compute_thresholds":{".class":"SymbolTableNode","kind":"Mdef","node":{".class":"FuncDef","abstract_status":0,"arg_kinds":[0,0,0],"arg_names":["self","endpoint","mutation_id"],"dataclass_transform_spec":null,"flags":[],"fullname":"cherenkov.openclaw.feedback.HealingFeedbackStore.compute_thresholds","name":"compute_thresholds","type":{".class":"CallableType","arg_kinds":[0,0,0],"arg_names":["self","endpoint","mutation_id"],"arg_types":["cherenkov.openclaw.feedback.HealingFeedbackStore","builtins.str","builtins.str"],"bound_args":[],"def_extras":{"first_arg":"self"},"fallback":"builtins.function","from_concatenate":false,"implicit":false,"imprecise_arg_kinds":false,"is_ellipsis_args":false,"name":"compute_thresholds of HealingFeedbackStore","ret_type":{".class":"Instance","args":["builtins.str",{".class":"AnyType","missing_import_name":null,"source_any":null,"type_of_any":2}],"type_ref":"builtins.dict"},"type_guard":null,"type_is":null,"unpack_kwargs":false,"variables":[]}}},"db_path":{".class":"SymbolTableNode","implicit":true,"kind":"Mdef","node":{".class":"Var","flags":["is_inferred"],"fullname":"cherenkov.openclaw.feedback.HealingFeedbackStore.db_path","name":"db_path","type":"builtins.str"}},"log":{".class":"SymbolTableNode","implicit":true,"kind":"Mdef","node":{".class":"Var","flags":["is_inferred"],"fullname":"cherenkov.openclaw.feedback.HealingFeedbackStore.log","name":"log","type":"cherenkov.core.errors.StructuredLogger"}},"record_feedback":{".class":"SymbolTableNode","kind":"Mdef","node":{".class":"FuncDef","abstract_status":0,"arg_kinds":[0,0,0,0,0,1,1],"arg_names":["self","item_id","endpoint","mutation_id","classification","actor","detail"],"dataclass_transform_spec":null,"flags":[],"fullname":"cherenkov.openclaw.feedback.HealingFeedbackStore.record_feedback","name":"record_feedback","type":{".class":"CallableType","arg_kinds":[0,0,0,0,0,1,1],"arg_names":["self","item_id","endpoint","mutation_id","classification","actor","detail"],"arg_types":["cherenkov.openclaw.feedback.HealingFeedbackStore","builtins.str","builtins.str","builtins.str","builtins.str","builtins.str","builtins.str"],"bound_args":[],"def_extras":{"first_arg":"self"},"fallback":"builtins.function","from_concatenate":false,"implicit":false,"imprecise_arg_kinds":false,"is_ellipsis_args":false,"name":"record_feedback of HealingFeedbackStore","ret_type":{".class":"NoneType"},"type_guard":null,"type_is":null,"unpack_kwargs":false,"variables":[]}}}},"self_type":{".class":"TypeVarType","default":{".class":"AnyType","missing_import_name":null,"source_any":null,"type_of_any":4},"fullname":"cherenkov.openclaw.feedback.HealingFeedbackStore.Self","id":0,"name":"Self","namespace":"","upper_bound":"cherenkov.openclaw.feedback.HealingFeedbackStore","values":[],"variance":0},"slots":null,"tuple_type":null,"type_vars":[],"typeddict_type":null}},"_BUSY_TIMEOUT_S":{".class":"SymbolTableNode","kind":"Gdef","node":{".class":"Var","flags":["is_ready","is_inferred","has_explicit_value"],"fullname":"cherenkov.openclaw.feedback._BUSY_TIMEOUT_S","name":"_BUSY_TIMEOUT_S","type":"builtins.float"}},"__annotations__":{".class":"SymbolTableNode","kind":"Gdef","node":{".class":"Var","flags":["is_ready"],"fullname":"cherenkov.openclaw.feedback.__annotations__","name":"__annotations__","type":{".class":"Instance","args":["builtins.str",{".class":"AnyType","missing_import_name":null,"source_any":null,"type_of_any":6}],"type_ref":"builtins.dict"}}},"__doc__":{".class":"SymbolTableNode","kind":"Gdef","node":{".class":"Var","flags":["is_ready"],"fullname":"cherenkov.openclaw.feedback.__doc__","name":"__doc__","type":"builtins.str"}},"__file__":{".class":"SymbolTableNode","kind":"Gdef","node":{".class":"Var","flags":["is_ready"],"fullname":"cherenkov.openclaw.feedback.__file__","name":"__file__","type":"builtins.str"}},"__name__":{".class":"SymbolTableNode","kind":"Gdef","node":{".class":"Var","flags":["is_ready"],"fullname":"cherenkov.openclaw.feedback.__name__","name":"__name__","type":"builtins.str"}},"__package__":{".class":"SymbolTableNode","kind":"Gdef","node":{".class":"Var","flags":["is_ready"],"fullname":"cherenkov.openclaw.feedback.__package__","name":"__package__","type":"builtins.str"}},"_default_db_path":{".class":"SymbolTableNode","kind":"Gdef","node":{".class":"FuncDef","abstract_status":0,"arg_kinds":[],"arg_names":[],"dataclass_transform_spec":null,"flags":[],"fullname":"cherenkov.openclaw.feedback._default_db_path","name":"_default_db_path","type":{".class":"CallableType","arg_kinds":[],"arg_names":[],"arg_types":[],"bound_args":[],"def_extras":{"first_arg":null},"fallback":"builtins.function","from_concatenate":false,"implicit":false,"imprecise_arg_kinds":false,"is_ellipsis_args":false,"name":"_default_db_path","ret_type":"builtins.str","type_guard":null,"type_is":null,"unpack_kwargs":false,"variables":[]}}},"annotations":{".class":"SymbolTableNode","cross_ref":"__future__.annotations","kind":"Gdef"},"get_logger":{".class":"SymbolTableNode","cross_ref":"cherenkov.core.errors.get_logger","kind":"Gdef"},"hashlib":{".class":"SymbolTableNode","cross_ref":"hashlib","kind":"Gdef"},"os":{".class":"SymbolTableNode","cross_ref":"os","kind":"Gdef"},"sqlite3":{".class":"SymbolTableNode","cross_ref":"sqlite3","kind":"Gdef"},"threading":{".class":"SymbolTableNode","cross_ref":"threading","kind":"Gdef"},"time":{".class":"SymbolTableNode","cross_ref":"time","kind":"Gdef"}},"path":"cherenkov\\openclaw\\feedback.py"}